splunk_log_handler
