Metadata-Version: 2.1
Name: splunk-log-handler
Version: 1.0.0
Summary: A log handler to send logs to a given splunk
Home-page: https://github.com/cuyu/splunk-log-handler
Author: Curtis Yu
Author-email: icyarm@icloud.com
License: MIT
Keywords: splunk,log handler
Platform: any
Classifier: Programming Language :: Python :: 2.7
Classifier: Programming Language :: Python :: 3.7
Provides-Extra: test
